__init__.py
logger.py
main.py
EternalTeleSales/__init__.py
EternalTeleSales/clean_EternalTeleSales.py
EternalTeleSales/data_assets/__init__.py
EternalTeleSales/data_assets/best_salesperson.py
EternalTeleSales/data_assets/department_breakdown.py
EternalTeleSales/data_assets/extra_insight_one.py
EternalTeleSales/data_assets/extra_insight_two.py
EternalTeleSales/data_assets/it_data.py
EternalTeleSales/data_assets/marketing_address_info.py
EternalTeleSales/data_assets/top_3.py
EternalTeleSales/data_assets/top_3_most_sold_per_department_netherlands.py
SalesData-0.1.0.dist-info/METADATA
SalesData-0.1.0.dist-info/WHEEL
SalesData-0.1.0.dist-info/entry_points.txt
SalesData-0.1.0.dist-info/top_level.txt
SalesData-0.1.0.dist-info/RECORD
